LICENSE
MANIFEST.in
README.md
setup.py
bin/x4c
x4c/__init__.py
x4c/case.py
x4c/core.py
x4c/diags.py
x4c/spell.py
x4c/utils.py
x4c/visual.py
x4c_exp.egg-info/PKG-INFO
x4c_exp.egg-info/SOURCES.txt
x4c_exp.egg-info/dependency_links.txt
x4c_exp.egg-info/not-zip-safe
x4c_exp.egg-info/requires.txt
x4c_exp.egg-info/top_level.txt