Metadata-Version: 2.1
Name: x4c-exp
Version: 2025.5.28
Summary: x4c: Xarray for CESM
Home-page: https://github.com/fzhu2e/x4c
Author: Feng Zhu
Author-email: fengzhu@ucar.edu
License: MIT
Keywords: Xarray,CESM,Climate Data Analysis and Visualization
Classifier: Natural Language :: English
Classifier: Programming Language :: Python :: 3.11
Classifier: Programming Language :: Python :: 3.12
License-File: LICENSE
Requires-Dist: netCDF4
Requires-Dist: xarray
Requires-Dist: dask
Requires-Dist: nc-time-axis
Requires-Dist: colorama
Requires-Dist: tqdm
Requires-Dist: xhistogram
